aqueduc/__main__.py
aqueduc/aqueduc.py
aqueduc-1.0.8.dist-info/LICENSE
aqueduc-1.0.8.dist-info/METADATA
aqueduc-1.0.8.dist-info/WHEEL
aqueduc-1.0.8.dist-info/entry_points.txt
aqueduc-1.0.8.dist-info/top_level.txt
aqueduc-1.0.8.dist-info/RECORD
