Metadata-Version: 2.1
Name: aqueduc
Version: 1.0.8
Author: Mozenn
License: Copyright 2024
Project-URL: Homepage, https://github.com/Mozenn/aqueduc
License-File: LICENSE
